Workbook

Sheet ブライト500
B1: 健康経営優良法人２０２１（中小規模法人部門（ブライト500））認定法人一覧
G2: 令和3年3月4日発表
G3: 令和3年4月1日更新
G4: 令和3年5月7日更新
G5: 令和3年6月4日更新
G6: 令和3年7月1日更新
G7: 令和3年8月1日更新
G8: 令和3年9月1日更新
G9: 令和3年10月1日更新
G10: 令和3年11月1日更新
G11: 令和3年12月1日更新
G12: 令和4年1月4日更新
G13: 令和4年2月1日更新
G14: (市区町村別・五十音順)
B15: No. | C15: 認定法人名 | D15: 法人番号 | E15: 都道府県 | F15: 市区町村 | G15: 業種
B16: 1 | C16: 勇建設株式会社 | D16: 1430001001408 | E16: 北海道 | F16: 札幌市 | G16: 建設業
B17: 2 | C17: 株式会社オープンソース | D17: 5430001039650 | E17: 北海道 | F17: 札幌市 | G17: その他
B18: 3 | C18: オリンポス債権回収 株式会社 | D18: 2430001036353 | E18: 北海道 | F18: 札幌市 | G18: 金融業
B19: 4 | C19: 主治医のような社会保険労務士法人 | D19: 4430005012679 | E19: 北海道 | F19: 札幌市 | G19: 専門・技術サービス業
B20: 5 | C20: 株式会社セイショウ | D20: 7430001029261 | E20: 北海道 | F20: 札幌市 | G20: サービス業（他に分類されないもの）
B21: 6 | C21: 株式会社北海道朝日航洋 | D21: 8430001022694 | E21: 北海道 | F21: 札幌市 | G21: 専門・技術サービス業
B22: 7 | C22: 株式会社近藤商会 | D22: 2440001000639 | E22: 北海道 | F22: 函館市 | G22: 卸売業
B23: 8 | C23: 株式会社エイブル保険事務所 | D23: 4450001006848 | E23: 北海道 | F23: 旭川市 | G23: 保険業
B24: 9 | C24: 株式会社片桐紙器 | D24: 7450001000807 | E24: 北海道 | F24: 旭川市 | G24: 製造業
B25: 10 | C25: 極東警備保障株式会社 | D25: 7450001000955 | E25: 北海道 | F25: 旭川市 | G25: サービス業（他に分類されないもの）
B26: 11 | C26: 株式会社美警 | D26: 6460001001391 | E26: 北海道 | F26: 釧路市 | G26: サービス業（他に分類されないもの）
B27: 12 | C27: 北王コンサルタント株式会社 | D27: 7460101001539 | E27: 北海道 | F27: 帯広市 | G27: 専門・技術サービス業
... B552: 537 | C552: 興南施設管理株式会社 | D552: 9360001008774 | E552: 沖縄県 | F552: 浦添市 | G552: 専門・技術サービス業

Sheet 優良法人（中小）
B1: 健康経営優良法人２０２１（中小規模法人部門）（※ブライト500を除く）認定法人一覧
G2: 令和3年3月4日発表
G3: 令和3年4月1日更新
G4: 令和3年5月7日更新
G5: 令和3年6月4日更新
G6: 令和3年7月1日更新
G7: 令和3年8月1日更新
G8: 令和3年9月1日更新
G9: 令和3年10月1日更新
G10: 令和3年11月1日更新
G11: 令和3年12月1日更新
G12: 令和4年1月4日更新
G13: 令和4年2月1日更新
G14: (市区町村別・五十音順)
B15: No. | C15: 認定法人名 | D15: 法人番号 | E15: 都道府県 | F15: 市区町村 | G15: 業種
B16: 1 | C16: アートシステム株式会社 | D16: 3430001001158 | E16: 北海道 | F16: 札幌市 | G16: 情報通信業
B17: 2 | C17: 株式会社アーバンクリアサポート | D17: 2430001041031 | E17: 北海道 | F17: 札幌市 | G17: サービス業（他に分類されないもの）
B18: 3 | C18: 株式会社ｉフォースラボ | D18: 6430001076841 | E18: 北海道 | F18: 札幌市 | G18: 情報通信業
B19: 4 | C19: ＡＵＲＡ ＡＲＣＨＩＴＥＣＴＳ株式会社 | D19: 6430001017267 | E19: 北海道 | F19: 札幌市 | G19: 建設業
B20: 5 | C20: 株式会社アットマークテクノ | D20: 5430001027135 | E20: 北海道 | F20: 札幌市 | G20: 製造業
B21: 6 | C21: 株式会社イーエス総合研究所 | D21: 7430001018801 | E21: 北海道 | F21: 札幌市 | G21: その他
B22: 7 | C22: 株式会社石山組 | D22: 3430001072835 | E22: 北海道 | F22: 札幌市 | G22: 建設業
B23: 8 | C23: 株式会社今井建設工業所 | D23: 1430001001713 | E23: 北海道 | F23: 札幌市 | G23: 建設業
B24: 9 | C24: Ｈ・Ｃ・Ｄ株式会社 | D24: 9430001062541 | E24: 北海道 | F24: 札幌市 | G24: 建設業
B25: 10 | C25: 株式会社ＡＫ Ｃｏｍｐａｎｙ | D25: 3430001074063 | E25: 北海道 | F25: 札幌市 | G25: 運輸業
B26: 11 | C26: 株式会社SOM | D26: 6430001076957 | E26: 北海道 | F26: 札幌市 | G26: 飲食サービス業
B27: 12 | C27: エスポワール不動産株式会社 | D27: 9430001002456 | E27: 北海道 | F27: 札幌市 | G27: 不動産業
... B7406: 7391 | C7406: 有限会社サキコーポレーション | D7406: 2360002018242 | E7406: 沖縄県 | F7406: 北谷町 | G7406: 不動産業

Sheet 都道府県別認定数
B2: 都道府県別 認定法人数
B4: 本社所在地の都道府県 | D4: 計 | F4: 本社所在地の都道府県 | H4: 計
B5: 北海道 | D5: =COUNTIF(ブライト500!E$16:E$552,都道府県別認定数!B5)+COUNTIF('優良法人（中小）'!E$16:E$7406,都道府県別認定数!B5) -> 270 | F5: 滋賀県 | H5: =COUNTIF(ブライト500!E$16:E$552,都道府県別認定数!F5)+COUNTIF('優良法人（中小）'!E$16:E$7406,都道府県別認定数!F5) -> 102
B6: 青森県 | D6: =COUNTIF(ブライト500!E$16:E$552,都道府県別認定数!B6)+COUNTIF('優良法人（中小）'!E$16:E$7406,都道府県別認定数!B6) -> 80 | F6: 京都府 | H6: =COUNTIF(ブライト500!E$16:E$552,都道府県別認定数!F6)+COUNTIF('優良法人（中小）'!E$16:E$7406,都道府県別認定数!F6) -> 162
B7: 岩手県 | D7: =COUNTIF(ブライト500!E$16:E$552,都道府県別認定数!B7)+COUNTIF('優良法人（中小）'!E$16:E$7406,都道府県別認定数!B7) -> 68 | F7: 大阪府 | H7: =COUNTIF(ブライト500!E$16:E$552,都道府県別認定数!F7)+COUNTIF('優良法人（中小）'!E$16:E$7406,都道府県別認定数!F7) -> 1099
B8: 宮城県 | D8: =COUNTIF(ブライト500!E$16:E$552,都道府県別認定数!B8)+COUNTIF('優良法人（中小）'!E$16:E$7406,都道府県別認定数!B8) -> 167 | F8: 兵庫県 | H8: =COUNTIF(ブライト500!E$16:E$552,都道府県別認定数!F8)+COUNTIF('優良法人（中小）'!E$16:E$7406,都道府県別認定数!F8) -> 434
B9: 秋田県 | D9: =COUNTIF(ブライト500!E$16:E$552,都道府県別認定数!B9)+COUNTIF('優良法人（中小）'!E$16:E$7406,都道府県別認定数!B9) -> 88 | F9: 奈良県 | H9: =COUNTIF(ブライト500!E$16:E$552,都道府県別認定数!F9)+COUNTIF('優良法人（中小）'!E$16:E$7406,都道府県別認定数!F9) -> 64
B10: 山形県 | D10: =COUNTIF(ブライト500!E$16:E$552,都道府県別認定数!B10)+COUNTIF('優良法人（中小）'!E$16:E$7406,都道府県別認定数!B10) -> 175 | F10: 和歌山県 | H10: =COUNTIF(ブライト500!E$16:E$552,都道府県別認定数!F10)+COUNTIF('優良法人（中小）'!E$16:E$7406,都道府県別認定数!F10) -> 44
B11: 福島県 | D11: =COUNTIF(ブライト500!E$16:E$552,都道府県別認定数!B11)+COUNTIF('優良法人（中小）'!E$16:E$7406,都道府県別認定数!B11) -> 189 | F11: 鳥取県 | H11: =COUNTIF(ブライト500!E$16:E$552,都道府県別認定数!F11)+COUNTIF('優良法人（中小）'!E$16:E$7406,都道府県別認定数!F11) -> 34
B12: 茨城県 | D12: =COUNTIF(ブライト500!E$16:E$552,都道府県別認定数!B12)+COUNTIF('優良法人（中小）'!E$16:E$7406,都道府県別認定数!B12) -> 54 | F12: 島根県 | H12: =COUNTIF(ブライト500!E$16:E$552,都道府県別認定数!F12)+COUNTIF('優良法人（中小）'!E$16:E$7406,都道府県別認定数!F12) -> 75
B13: 栃木県 | D13: =COUNTIF(ブライト500!E$16:E$552,都道府県別認定数!B13)+COUNTIF('優良法人（中小）'!E$16:E$7406,都道府県別認定数!B13) -> 99 | F13: 岡山県 | H13: =COUNTIF(ブライト500!E$16:E$552,都道府県別認定数!F13)+COUNTIF('優良法人（中小）'!E$16:E$7406,都道府県別認定数!F13) -> 245
B14: 群馬県 | D14: =COUNTIF(ブライト500!E$16:E$552,都道府県別認定数!B14)+COUNTIF('優良法人（中小）'!E$16:E$7406,都道府県別認定数!B14) -> 138 | F14: 広島県 | H14: =COUNTIF(ブライト500!E$16:E$552,都道府県別認定数!F14)+COUNTIF('優良法人（中小）'!E$16:E$7406,都道府県別認定数!F14) -> 146
B15: 埼玉県 | D15: =COUNTIF(ブライト500!E$16:E$552,都道府県別認定数!B15)+COUNTIF('優良法人（中小）'!E$16:E$7406,都道府県別認定数!B15) -> 147 | F15: 山口県 | H15: =COUNTIF(ブライト500!E$16:E$552,都道府県別認定数!F15)+COUNTIF('優良法人（中小）'!E$16:E$7406,都道府県別認定数!F15) -> 68
B16: 千葉県 | D16: =COUNTIF(ブライト500!E$16:E$552,都道府県別認定数!B16)+COUNTIF('優良法人（中小）'!E$16:E$7406,都道府県別認定数!B16) -> 119 | F16: 徳島県 | H16: =COUNTIF(ブライト500!E$16:E$552,都道府県別認定数!F16)+COUNTIF('優良法人（中小）'!E$16:E$7406,都道府県別認定数!F16) -> 46
... B27: 愛知県 | D27: =COUNTIF(ブライト500!E$16:E$552,都道府県別認定数!B27)+COUNTIF('優良法人（中小）'!E$16:E$7406,都道府県別認定数!B27) -> 927 | F27: 沖縄県 | H27: =COUNTIF(ブライト500!E$16:E$552,都道府県別認定数!F27)+COUNTIF('優良法人（中小）'!E$16:E$7406,都道府県別認定数!F27) -> 36
B28: 三重県 | D28: =COUNTIF(ブライト500!E$16:E$552,都道府県別認定数!B28)+COUNTIF('優良法人（中小）'!E$16:E$7406,都道府県別認定数!B28) -> 185 | F28: 合計 | H28: =SUM(H5:H27,D5:D28) -> 7928

Sheet 業種別認定数
B2: 業種別 認定法人数
B4: 業種名 | E4: 認定法人数 | G4: 業種名 | J4: 認定法人数
B5: 会社法上の会社等、士業法人、その他、国内法に基づく法人 | E5: =SUM(E6:E38) -> 7507 | G5: 特定非営利活動法人 | J5: =COUNTIF(ブライト500!G$16:G$552,業種別認定数!G5)+COUNTIF('優良法人（中小）'!G$16:G$7406,業種別認定数!G5) -> 20
C6: 農業 | E6: =COUNTIF(ブライト500!G$16:G$552,業種別認定数!C6)+COUNTIF('優良法人（中小）'!G$16:G$7406,業種別認定数!C6) -> 5 | G6: 医療法人、社会福祉法人、健康保険組合等保険者 | J6: =COUNTIF(ブライト500!G$16:G$552,業種別認定数!G6)+COUNTIF('優良法人（中小）'!G$16:G$7406,業種別認定数!G6) -> 146
C7: 林業 | E7: =COUNTIF(ブライト500!G$16:G$552,業種別認定数!C7)+COUNTIF('優良法人（中小）'!G$16:G$7406,業種別認定数!C7) -> 7 | G7: 社団法人、財団法人、商工会議所・商工会 | J7: =COUNTIF(ブライト500!G$16:G$552,業種別認定数!G7)+COUNTIF('優良法人（中小）'!G$16:G$7406,業種別認定数!G7) -> 235
C8: 漁業 | E8: =COUNTIF(ブライト500!G$16:G$552,業種別認定数!C8)+COUNTIF('優良法人（中小）'!G$16:G$7406,業種別認定数!C8) -> 2 | G8: 公法人、特殊法人（地方公共団体、独立行政法人、公共組合、公団、公社、事業団等） | J8: =COUNTIF(ブライト500!G$16:G$552,業種別認定数!G8)+COUNTIF('優良法人（中小）'!G$16:G$7406,業種別認定数!G8) -> 20
C9: 鉱業 | E9: =COUNTIF(ブライト500!G$16:G$552,業種別認定数!C9)+COUNTIF('優良法人（中小）'!G$16:G$7406,業種別認定数!C9) -> 1 | G9: 合計 | J9: =SUM(E5,J5:J8) -> 7928
C10: 採石業 | E10: =COUNTIF(ブライト500!G$16:G$552,業種別認定数!C10)+COUNTIF('優良法人（中小）'!G$16:G$7406,業種別認定数!C10) -> 3
C11: 砂利採取業 | E11: =COUNTIF(ブライト500!G$16:G$552,業種別認定数!C11)+COUNTIF('優良法人（中小）'!G$16:G$7406,業種別認定数!C11) -> 0
C12: 建設業 | E12: =COUNTIF(ブライト500!G$16:G$552,業種別認定数!C12)+COUNTIF('優良法人（中小）'!G$16:G$7406,業種別認定数!C12) -> 1574
C13: 製造業 | E13: =COUNTIF(ブライト500!G$16:G$552,業種別認定数!C13)+COUNTIF('優良法人（中小）'!G$16:G$7406,業種別認定数!C13) -> 1690
C14: 電気・ガス・熱供給・水道業 | E14: =COUNTIF(ブライト500!G$16:G$552,業種別認定数!C14)+COUNTIF('優良法人（中小）'!G$16:G$7406,業種別認定数!C14) -> 55
C15: 情報通信業 | E15: =COUNTIF(ブライト500!G$16:G$552,業種別認定数!C15)+COUNTIF('優良法人（中小）'!G$16:G$7406,業種別認定数!C15) -> 329
C16: 運輸業 | E16: =COUNTIF(ブライト500!G$16:G$552,業種別認定数!C16)+COUNTIF('優良法人（中小）'!G$16:G$7406,業種別認定数!C16) -> 660
C17: 郵便業 | E17: =COUNTIF(ブライト500!G$16:G$552,業種別認定数!C17)+COUNTIF('優良法人（中小）'!G$16:G$7406,業種別認定数!C17) -> 1
C18: 卸売業 | E18: =COUNTIF(ブライト500!G$16:G$552,業種別認定数!C18)+COUNTIF('優良法人（中小）'!G$16:G$7406,業種別認定数!C18) -> 534
C19: 小売業 | E19: =COUNTIF(ブライト500!G$16:G$552,業種別認定数!C19)+COUNTIF('優良法人（中小）'!G$16:G$7406,業種別認定数!C19) -> 397
C20: 金融業 | E20: =COUNTIF(ブライト500!G$16:G$552,業種別認定数!C20)+COUNTIF('優良法人（中小）'!G$16:G$7406,業種別認定数!C20) -> 130
C21: 保険業 | E21: =COUNTIF(ブライト500!G$16:G$552,業種別認定数!C21)+COUNTIF('優良法人（中小）'!G$16:G$7406,業種別認定数!C21) -> 428
... C38: 不明 | E38: =COUNTIF(ブライト500!G$16:G$552,業種別認定数!C38)+COUNTIF('優良法人（中小）'!G$16:G$7406,業種別認定数!C38) -> 1
